{
  "section": "horoscope",
  "keys": {
    "horoscope.2026.zodiac.aries.name": {
      "en": "Aries",
      "hi": "मेष",
      "ta": "மேஷம்",
      "te": "మేషం",
      "bn": "মেষ",
      "mr": "मेष",
      "gu": "મેષ",
      "kn": "ಮೇಷ",
      "ml": "മേടം",
      "pa": "ਮੇਖ"
    },
    "horoscope.2026.zodiac.aries.hindi": {
      "en": "मेष",
      "hi": "मेष",
      "ta": "மேஷம்",
      "te": "మేషం",
      "bn": "মেষ",
      "mr": "मेष",
      "gu": "મેષ",
      "kn": "ಮೇಷ",
      "ml": "മേടം",
      "pa": "ਮੇਖ"
    },
    "horoscope.2026.zodiac.aries.overview": {
      "en": "2026 brings transformative energy for Aries. Jupiter's influence in the first half promises career growth, while Saturn encourages financial discipline. Love life sees positive developments after mid-year.",
      "hi": "2026 मेष राशि के लिए परिवर्तनकारी ऊर्जा लाता है। पहली छमाही में बृहस्पति का प्रभाव करियर में वृद्धि का वादा करता है, जबकि शनि वित्तीय अनुशासन को प्रोत्साहित करता है। मध्य वर्ष के बाद प्रेम जीवन में सकारात्मक विकास होता है।",
      "ta": "2026 மேஷத்திற்கு மாற்றும் ஆற்றலைக் கொண்டுவருகிறது। முதல் பாதியில் குருவின் தாக்கம் தொழில் வளர்ச்சியை உறுதியளிக்கிறது, சனி நிதி ஒழுக்கத்தை ஊக்குவிக்கிறது। ஆண்டின் நடுப்பகுதிக்குப் பிறகு காதல் வாழ்க்கை நேர்மறையான வளர்ச்சியைக் காண்கிறது।",
      "te": "2026 మేషానికి పరివర్తన శక్తిని తెస్తుంది. మొదటి సగంలో గురు ప్రభావం కెరీర్ వృద్ధిని వాగ్దానం చేస్తుంది, శని ఆర్థిక క్రమశిక్షణను ప్రోత్సహిస్తుంది. సంవత్సరం మధ్య తర్వాత ప్రేమ జీవితం సానుకూల పరిణామాలను చూస్తుంది.",
      "bn": "2026 মেষের জন্য রূপান্তরকারী শক্তি নিয়ে আসে। প্রথমার্ধে বৃহস্পতির প্রভাব কর্মজীবনে বৃদ্ধির প্রতিশ্রুতি দেয়, শনি আর্থিক শৃঙ্খলাকে উৎসাহিত করে। বছরের মাঝামাঝি পরে প্রেম জীবনে ইতিবাচক উন্নয়ন দেখা যায়।",
      "mr": "2026 मेषसाठी परिवर्तनकारी ऊर्जा आणते. पहिल्या सहामाहीत गुरूचा प्रभाव करिअरमध्ये वाढीचे वचन देतो, तर शनि आर्थिक शिस्तीला प्रोत्साहन देतो. वर्षाच्या मध्यानंतर प्रेम जीवनात सकारात्मक विकास होतो.",
      "gu": "2026 મેષ માટે પરિવર્તનકારી ઊર્જા લાવે છે. પ્રથમ અર્ધમાં ગુરુનો પ્રભાવ કારકિર્દી વૃદ્ધિનું વચન આપે છે, શનિ નાણાકીય શિસ્તને પ્રોત્સાહિત કરે છે. વર્ષના મધ્ય પછી પ્રેમ જીવનમાં સકારાત્મક વિકાસ જોવા મળે છે.",
      "kn": "2026 ಮೇಷಕ್ಕೆ ಪರಿವರ್ತನಾ ಶಕ್ತಿಯನ್ನು ತರುತ್ತದೆ. ಮೊದಲ ಅರ್ಧದಲ್ಲಿ ಗುರುವಿನ ಪ್ರಭಾವವು ವೃತ್ತಿ ಬೆಳವಣಿಗೆಯನ್ನು ಭರವಸೆ ನೀಡುತ್ತದೆ, ಶನಿ ಆರ್ಥಿಕ ಶಿಸ್ತನ್ನು ಪ್ರೋತ್ಸಾಹಿಸುತ್ತದೆ. ವರ್ಷದ ಮಧ್ಯದ ನಂತರ ಪ್ರೇಮ ಜೀವನವು ಸಕಾರಾತ್ಮಕ ಬೆಳವಣಿಗೆಗಳನ್ನು ಕಾಣುತ್ತದೆ.",
      "ml": "2026 മേടത്തിന് പരിവർത്തന ഊർജ്ജം കൊണ്ടുവരുന്നു. ആദ്യ പകുതിയിൽ വ്യാഴത്തിന്റെ സ്വാധീനം കരിയർ വളർച്ച വാഗ്ദാനം ചെയ്യുന്നു, ശനി സാമ്പത്തിക അച്ചടക്കത്തെ പ്രോത്സാഹിപ്പിക്കുന്നു. വർഷത്തിന്റെ മധ്യത്തിന് ശേഷം പ്രണയ ജീവിതം നല്ല വികസനങ്ങൾ കാണുന്നു.",
      "pa": "2026 ਮੇਖ ਲਈ ਪਰਿਵਰਤਨਸ਼ੀਲ ਊਰਜਾ ਲਿਆਉਂਦਾ ਹੈ। ਪਹਿਲੇ ਅੱਧ ਵਿੱਚ ਗੁਰੂ ਦਾ ਪ੍ਰਭਾਵ ਕਰੀਅਰ ਵਿਕਾਸ ਦਾ ਵਾਅਦਾ ਕਰਦਾ ਹੈ, ਸ਼ਨੀ ਵਿੱਤੀ ਅਨੁਸ਼ਾਸਨ ਨੂੰ ਉਤਸ਼ਾਹਿਤ ਕਰਦਾ ਹੈ। ਸਾਲ ਦੇ ਮੱਧ ਤੋਂ ਬਾਅਦ ਪਿਆਰ ਦੀ ਜ਼ਿੰਦਗੀ ਸਕਾਰਾਤਮਕ ਵਿਕਾਸ ਦੇਖਦੀ ਹੈ।"
    },
    "horoscope.2026.zodiac.aries.highlight1": {
      "en": "Career breakthrough in Q2",
      "hi": "Q2 में करियर में सफलता",
      "ta": "Q2 இல் தொழில் முன்னேற்றம்",
      "te": "Q2లో కెరీర్ విజయం",
      "bn": "Q2-তে কর্মজীবনে সাফল্য",
      "mr": "Q2 मध्ये करिअरमध्ये यश",
      "gu": "Q2માં કારકિર્દીમાં સફળતા",
      "kn": "Q2ರಲ್ಲಿ ವೃತ್ತಿ ಯಶಸ್ಸು",
      "ml": "Q2-ൽ കരിയർ വിജയം",
      "pa": "Q2 ਵਿੱਚ ਕਰੀਅਰ ਸਫਲਤਾ"
    },
    "horoscope.2026.zodiac.aries.highlight2": {
      "en": "New relationship opportunities",
      "hi": "नए रिश्तों के अवसर",
      "ta": "புதிய உறவு வாய்ப்புகள்",
      "te": "కొత్త సంబంధ అవకాశాలు",
      "bn": "নতুন সম্পর্কের সুযোগ",
      "mr": "नवीन नातेसंबंधांच्या संधी",
      "gu": "નવા સંબંધોની તકો",
      "kn": "ಹೊಸ ಸಂಬಂಧ ಅವಕಾಶಗಳು",
      "ml": "പുതിയ ബന്ധ അവസരങ്ങൾ",
      "pa": "ਨਵੇਂ ਰਿਸ਼ਤਿਆਂ ਦੇ ਮੌਕੇ"
    },
    "horoscope.2026.zodiac.aries.highlight3": {
      "en": "Property investments favorable",
      "hi": "संपत्ति निवेश अनुकूल",
      "ta": "சொத்து முதலீடுகள் சாதகமானவை",
      "te": "ఆస్తి పెట్టుబడులు అనుకూలం",
      "bn": "সম্পত্তি বিনিয়োগ অনুকূল",
      "mr": "मालमत्ता गुंतवणूक अनुकूल",
      "gu": "મિલકત રોકાણો અનુકૂળ",
      "kn": "ಆಸ್ತಿ ಹೂಡಿಕೆಗಳು ಅನುಕೂಲಕರ",
      "ml": "സ്വത്ത് നിക്ഷേപങ്ങൾ അനുകൂലം",
      "pa": "ਜਾਇਦਾਦ ਨਿਵੇਸ਼ ਅਨੁਕੂਲ"
    },
    "horoscope.2026.zodiac.taurus.name": {
      "en": "Taurus",
      "hi": "वृषभ",
      "ta": "ரிஷபம்",
      "te": "వృషభం",
      "bn": "বৃষ",
      "mr": "वृषभ",
      "gu": "વૃષભ",
      "kn": "ವೃಷಭ",
      "ml": "ഇടവം",
      "pa": "ਬ੍ਰਿਖ"
    },
    "horoscope.2026.zodiac.taurus.hindi": {
      "en": "वृषभ",
      "hi": "वृषभ",
      "ta": "ரிஷபம்",
      "te": "వృషభం",
      "bn": "বৃষ",
      "mr": "वृषभ",
      "gu": "વૃષભ",
      "kn": "ವೃಷಭ",
      "ml": "ഇടവം",
      "pa": "ਬ੍ਰਿਖ"
    },
    "horoscope.2026.zodiac.taurus.overview": {
      "en": "A year of stability and growth for Taurus. Financial gains are indicated, especially through investments. Relationships deepen, and health requires attention in the latter half.",
      "hi": "वृषभ के लिए स्थिरता और विकास का वर्ष। विशेष रूप से निवेश के माध्यम से वित्तीय लाभ संकेतित है। रिश्ते गहरे होते हैं, और दूसरी छमाही में स्वास्थ्य पर ध्यान देने की आवश्यकता है।",
      "ta": "ரிஷபத்திற்கு நிலைத்தன்மை மற்றும் வளர்ச்சியின் ஆண்டு. குறிப்பாக முதலீடுகள் மூலம் நிதி ஆதாயங்கள் சுட்டிக்காட்டப்படுகின்றன. உறவுகள் ஆழமாகின்றன, பிற்பகுதியில் ஆரோக்கியத்திற்கு கவனம் தேவை.",
      "te": "వృషభానికి స్థిరత్వం మరియు వృద్ధి సంవత్సరం. ముఖ్యంగా పెట్టుబడుల ద్వారా ఆర్థిక లాభాలు సూచించబడ్డాయి. సంబంధాలు లోతుగా మారతాయి, రెండవ సగంలో ఆరోగ్యానికి శ్రద్ధ అవసరం.",
      "bn": "বৃষের জন্য স্থিতিশীলতা এবং বৃদ্ধির বছর। বিশেষত বিনিয়োগের মাধ্যমে আর্থিক লাভ নির্দেশিত। সম্পর্ক গভীর হয়, এবং দ্বিতীয়ার্ধে স্বাস্থ্যের প্রতি মনোযোগ প্রয়োজন।",
      "mr": "वृषभसाठी स्थिरता आणि वाढीचे वर्ष. विशेषतः गुंतवणुकीद्वारे आर्थिक लाभ दर्शविला जातो. नातेसंबंध गहिरे होतात आणि दुसऱ्या सहामाहीत आरोग्याकडे लक्ष देणे आवश्यक आहे.",
      "gu": "વૃષભ માટે સ્થિરતા અને વૃદ્ધિનું વર્ષ. ખાસ કરીને રોકાણો દ્વારા નાણાકીય લાભો સૂચવવામાં આવે છે. સંબંધો ઊંડા થાય છે, અને બીજા અર્ધમાં આરોગ્ય પર ધ્યાન આપવાની જરૂર છે.",
      "kn": "ವೃಷಭಕ್ಕೆ ಸ್ಥಿರತೆ ಮತ್ತು ಬೆಳವಣಿಗೆಯ ವರ್ಷ. ವಿಶೇಷವಾಗಿ ಹೂಡಿಕೆಗಳ ಮೂಲಕ ಆರ್ಥಿಕ ಲಾಭಗಳು ಸೂಚಿಸಲಾಗಿದೆ. ಸಂಬಂಧಗಳು ಆಳವಾಗುತ್ತವೆ, ಮತ್ತು ಎರಡನೇ ಅರ್ಧದಲ್ಲಿ ಆರೋಗ್ಯಕ್ಕೆ ಗಮನ ಬೇಕು.",
      "ml": "ഇടവത്തിന് സ്ഥിരതയുടെയും വളർച്ചയുടെയും വർഷം. പ്രത്യേകിച്ച് നിക്ഷേപങ്ങളിലൂടെ സാമ്പത്തിക നേട്ടങ്ങൾ സൂചിപ്പിക്കുന്നു. ബന്ധങ്ങൾ ആഴത്തിലാകുന്നു, രണ്ടാം പകുതിയിൽ ആരോഗ്യത്തിന് ശ്രദ്ധ ആവശ്യമാണ്.",
      "pa": "ਬ੍ਰਿਖ ਲਈ ਸਥਿਰਤਾ ਅਤੇ ਵਿਕਾਸ ਦਾ ਸਾਲ। ਖਾਸ ਕਰਕੇ ਨਿਵੇਸ਼ਾਂ ਰਾਹੀਂ ਵਿੱਤੀ ਲਾਭ ਦਰਸਾਏ ਗਏ ਹਨ। ਰਿਸ਼ਤੇ ਡੂੰਘੇ ਹੁੰਦੇ ਹਨ, ਅਤੇ ਦੂਜੇ ਅੱਧ ਵਿੱਚ ਸਿਹਤ ਵੱਲ ਧਿਆਨ ਦੇਣ ਦੀ ਲੋੜ ਹੈ।"
    },
    "horoscope.2026.zodiac.taurus.highlight1": {
      "en": "Strong financial gains",
      "hi": "मजबूत वित्तीय लाभ",
      "ta": "வலுவான நிதி ஆதாயங்கள்",
      "te": "బలమైన ఆర్థిక లాభాలు",
      "bn": "শক্তিশালী আর্থিক লাভ",
      "mr": "मजबूत आर्थिक लाभ",
      "gu": "મજબૂત નાણાકીય લાભ",
      "kn": "ಬಲವಾದ ಆರ್ಥಿಕ ಲಾಭಗಳು",
      "ml": "ശക്തമായ സാമ്പത്തിക നേട്ടങ്ങൾ",
      "pa": "ਮਜ਼ਬੂਤ ਵਿੱਤੀ ਲਾਭ"
    },
    "horoscope.2026.zodiac.taurus.highlight2": {
      "en": "Marriage prospects for singles",
      "hi": "अविवाहितों के लिए विवाह की संभावनाएं",
      "ta": "தனிமையானவர்களுக்கு திருமண வாய்ப்புகள்",
      "te": "సింగిల్స్ కోసం వివాహ అవకాశాలు",
      "bn": "অবিবাহিতদের জন্য বিবাহের সম্ভাবনা",
      "mr": "अविवाहितांसाठी विवाहाच्या शक्यता",
      "gu": "સિંગલ્સ માટે લગ્નની સંભાવનાઓ",
      "kn": "ಸಿಂಗಲ್ಸ್‌ಗೆ ಮದುವೆ ಅವಕಾಶಗಳು",
      "ml": "സിംഗിൾസിന് വിവാഹ സാധ്യതകൾ",
      "pa": "ਸਿੰਗਲਜ਼ ਲਈ ਵਿਆਹ ਦੀਆਂ ਸੰਭਾਵਨਾਵਾਂ"
    },
    "horoscope.2026.zodiac.taurus.highlight3": {
      "en": "Health focus needed in Q4",
      "hi": "Q4 में स्वास्थ्य पर ध्यान देने की जरूरत",
      "ta": "Q4 இல் ஆரோக்கியத்தில் கவனம் தேவை",
      "te": "Q4లో ఆరోగ్యంపై దృష్టి అవసరం",
      "bn": "Q4-তে স্বাস্থ্যের উপর মনোযোগ প্রয়োজন",
      "mr": "Q4 मध्ये आरोग्यावर लक्ष देणे आवश्यक",
      "gu": "Q4માં આરોગ્ય પર ધ્યાન જરૂરી",
      "kn": "Q4ರಲ್ಲಿ ಆರೋಗ್ಯದ ಮೇಲೆ ಗಮನ ಬೇಕು",
      "ml": "Q4-ൽ ആരോഗ്യത്തിൽ ശ്രദ്ധ ആവശ്യം",
      "pa": "Q4 ਵਿੱਚ ਸਿਹਤ 'ਤੇ ਧਿਆਨ ਦੇਣ ਦੀ ਲੋੜ"
    },
    "horoscope.2026.zodiac.gemini.name": {
      "en": "Gemini",
      "hi": "मिथुन",
      "ta": "மிதுனம்",
      "te": "మిథునం",
      "bn": "মিথুন",
      "mr": "मिथुन",
      "gu": "મિથુન",
      "kn": "ಮಿಥುನ",
      "ml": "മിഥുനം",
      "pa": "ਮਿਥੁਨ"
    },
    "horoscope.2026.zodiac.gemini.hindi": {
      "en": "मिथुन",
      "hi": "मिथुन",
      "ta": "மிதுனம்",
      "te": "మిథునం",
      "bn": "মিথুন",
      "mr": "मिथुन",
      "gu": "મિથુન",
      "kn": "ಮಿಥುನ",
      "ml": "മിഥുനം",
      "pa": "ਮਿਥੁਨ"
    },
    "horoscope.2026.zodiac.gemini.overview": {
      "en": "Communication and networking bring success in 2026. Career changes are possible, and travel opportunities arise. Love life may face some challenges requiring patience.",
      "hi": "2026 में संचार और नेटवर्किंग सफलता लाते हैं। करियर में बदलाव संभव हैं, और यात्रा के अवसर उत्पन्न होते हैं। प्रेम जीवन में कुछ चुनौतियां आ सकती हैं जिनमें धैर्य की आवश्यकता होती है।",
      "ta": "2026 இல் தொடர்பு மற்றும் நெட்வொர்க்கிங் வெற்றியைக் கொண்டுவருகின்றன. தொழில் மாற்றங்கள் சாத்தியம், பயண வாய்ப்புகள் எழுகின்றன. காதல் வாழ்க்கை பொறுமை தேவைப்படும் சில சவால்களை எதிர்கொள்ளலாம்.",
      "te": "2026లో కమ్యూనికేషన్ మరియు నెట్‌వర్కింగ్ విజయాన్ని తెస్తాయి. కెరీర్ మార్పులు సాధ్యం, ప్రయాణ అవకాశాలు తలెత్తుతాయి. ప్రేమ జీవితం ఓపిక అవసరమయ్యే కొన్ని సవాళ్లను ఎదుర్కోవచ్చు.",
      "bn": "2026-এ যোগাযোগ এবং নেটওয়ার্কিং সাফল্য আনে। কর্মজীবনে পরিবর্তন সম্ভব, এবং ভ্রমণের সুযোগ তৈরি হয়। প্রেম জীবনে কিছু চ্যালেঞ্জের মুখোমুখি হতে পারে যার জন্য ধৈর্য প্রয়োজন।",
      "mr": "2026 मध्ये संवाद आणि नेटवर्किंग यश आणतात. करिअरमध्ये बदल शक्य आहेत आणि प्रवासाच्या संधी निर्माण होतात. प्रेम जीवनात काही आव्हाने येऊ शकतात ज्यासाठी संयम आवश्यक आहे.",
      "gu": "2026માં સંચાર અને નેટવર્કિંગ સફળતા લાવે છે. કારકિર્દીમાં ફેરફારો શક્ય છે, અને મુસાફરીની તકો ઊભી થાય છે. પ્રેમ જીવનમાં કેટલીક પડકારોનો સામનો કરવો પડી શકે છે જેમાં ધીરજની જરૂર છે.",
      "kn": "2026ರಲ್ಲಿ ಸಂವಹನ ಮತ್ತು ನೆಟ್‌ವರ್ಕಿಂಗ್ ಯಶಸ್ಸನ್ನು ತರುತ್ತವೆ. ವೃತ್ತಿ ಬದಲಾವಣೆಗಳು ಸಾಧ್ಯ, ಮತ್ತು ಪ್ರಯಾಣ ಅವಕಾಶಗಳು ಉದ್ಭವಿಸುತ್ತವೆ. ಪ್ರೇಮ ಜೀವನವು ತಾಳ್ಮೆ ಅಗತ್ಯವಿರುವ ಕೆಲವು ಸವಾಲುಗಳನ್ನು ಎದುರಿಸಬಹುದು.",
      "ml": "2026-ൽ ആശയവിനിമയവും നെറ്റ്‌വർക്കിംഗും വിജയം കൊണ്ടുവരുന്നു. കരിയർ മാറ്റങ്ങൾ സാധ്യമാണ്, യാത്രാ അവസരങ്ങൾ ഉണ്ടാകുന്നു. പ്രണയ ജീവിതം ക്ഷമ ആവശ്യമുള്ള ചില വെല്ലുവിളികൾ നേരിടാം.",
      "pa": "2026 ਵਿੱਚ ਸੰਚਾਰ ਅਤੇ ਨੈੱਟਵਰਕਿੰਗ ਸਫਲਤਾ ਲਿਆਉਂਦੇ ਹਨ। ਕਰੀਅਰ ਵਿੱਚ ਬਦਲਾਅ ਸੰਭਵ ਹਨ, ਅਤੇ ਯਾਤਰਾ ਦੇ ਮੌਕੇ ਪੈਦਾ ਹੁੰਦੇ ਹਨ। ਪਿਆਰ ਦੀ ਜ਼ਿੰਦਗੀ ਨੂੰ ਕੁਝ ਚੁਣੌਤੀਆਂ ਦਾ ਸਾਹਮਣਾ ਕਰਨਾ ਪੈ ਸਕਦਾ ਹੈ ਜਿਨ੍ਹਾਂ ਲਈ ਧੀਰਜ ਦੀ ਲੋੜ ਹੈ।"
    },
    "horoscope.2026.zodiac.gemini.highlight1": {
      "en": "Career advancement through networking",
      "hi": "नेटवर्किंग के माध्यम से करियर में उन्नति",
      "ta": "நெட்வொர்க்கிங் மூலம் தொழில் முன்னேற்றம்",
      "te": "నెట్‌వర్కింగ్ ద్వారా కెరీర్ అభివృద్ధి",
      "bn": "নেটওয়ার্কিংয়ের মাধ্যমে কর্মজীবনে উন্নতি",
      "mr": "नेटवर्किंगद्वारे करिअरमध्ये प्रगती",
      "gu": "નેટવર્કિંગ દ્વારા કારકિર્દીમાં પ્રગતિ",
      "kn": "ನೆಟ್‌ವರ್ಕಿಂಗ್ ಮೂಲಕ ವೃತ್ತಿ ಪ್ರಗತಿ",
      "ml": "നെറ്റ്‌വർക്കിംഗിലൂടെ കരിയർ പുരോഗതി",
      "pa": "ਨੈੱਟਵਰਕਿੰਗ ਰਾਹੀਂ ਕਰੀਅਰ ਤਰੱਕੀ"
    },
    "horoscope.2026.zodiac.gemini.highlight2": {
      "en": "International travel likely",
      "hi": "अंतर्राष्ट्रीय यात्रा की संभावना",
      "ta": "சர்வதேச பயணம் சாத்தியம்",
      "te": "అంతర్జాతీయ ప్రయాణం సంభావ్యం",
      "bn": "আন্তর্জাতিক ভ্রমণ সম্ভব",
      "mr": "आंतरराष्ट्रीय प्रवास शक्य",
      "gu": "આંતરરાષ્ટ્રીય મુસાફરી સંભવ",
      "kn": "ಅಂತರರಾಷ್ಟ್ರೀಯ ಪ್ರಯಾಣ ಸಾಧ್ಯ",
      "ml": "അന്താരാഷ്ട്ര യാത്ര സാധ്യം",
      "pa": "ਅੰਤਰਰਾਸ਼ਟਰੀ ਯਾਤਰਾ ਸੰਭਵ"
    },
    "horoscope.2026.zodiac.gemini.highlight3": {
      "en": "Communication skills shine",
      "hi": "संचार कौशल चमकते हैं",
      "ta": "தொடர்பு திறன்கள் பிரகாசிக்கின்றன",
      "te": "కమ్యూనికేషన్ నైపుణ్యాలు ప్రకాశిస్తాయి",
      "bn": "যোগাযোগ দক্ষতা উজ্জ্বল হয়",
      "mr": "संवाद कौशल्य चमकते",
      "gu": "સંચાર કૌશલ્ય ચમકે છે",
      "kn": "ಸಂವಹನ ಕೌಶಲ್ಯಗಳು ಹೊಳೆಯುತ್ತವೆ",
      "ml": "ആശയവിനിമയ കഴിവുകൾ തിളങ്ങുന്നു",
      "pa": "ਸੰਚਾਰ ਹੁਨਰ ਚਮਕਦੇ ਹਨ"
    },
    "horoscope.2026.zodiac.cancer.name": {
      "en": "Cancer",
      "hi": "कर्क",
      "ta": "கடகம்",
      "te": "కర్కాటకం",
      "bn": "কর্কট",
      "mr": "कर्क",
      "gu": "કર્ક",
      "kn": "ಕರ್ಕಾಟಕ",
      "ml": "കർക്കടകം",
      "pa": "ਕਰਕ"
    },
    "horoscope.2026.zodiac.cancer.hindi": {
      "en": "कर्क",
      "hi": "कर्क",
      "ta": "கடகம்",
      "te": "కర్కాటకం",
      "bn": "কর্কট",
      "mr": "कर्क",
      "gu": "કર્ક",
      "kn": "ಕರ್ಕಾಟಕ",
      "ml": "കർക്കടകം",
      "pa": "ਕਰਕ"
    },
    "horoscope.2026.zodiac.cancer.overview": {
      "en": "Home and family take center stage in 2026. Property matters resolve favorably. Career sees steady progress, and emotional well-being improves significantly.",
      "hi": "2026 में घर और परिवार केंद्र में रहते हैं। संपत्ति के मामले अनुकूल रूप से हल होते हैं। करियर में स्थिर प्रगति होती है, और भावनात्मक कल्याण में काफी सुधार होता है।",
      "ta": "2026 இல் வீடும் குடும்பமும் மையமாக இருக்கின்றன. சொத்து விஷயங்கள் சாதகமாக தீர்க்கப்படுகின்றன. தொழில் நிலையான முன்னேற்றத்தைக் காண்கிறது, உணர்ச்சி நலன் கணிசமாக மேம்படுகிறது.",
      "te": "2026లో ఇల్లు మరియు కుటుంబం కేంద్ర స్థానంలో ఉంటాయి. ఆస్తి విషయాలు అనుకూలంగా పరిష్కరించబడతాయి. కెరీర్ స్థిరమైన పురోగతిని చూస్తుంది, మరియు భావోద్వేగ శ్రేయస్సు గణనీయంగా మెరుగుపడుతుంది.",
      "bn": "2026-এ বাড়ি এবং পরিবার কেন্দ্রে থাকে। সম্পত্তির বিষয়গুলি অনুকূলভাবে সমাধান হয়। কর্মজীবনে স্থির অগ্রগতি দেখা যায়, এবং মানসিক সুস্থতা উল্লেখযোগ্যভাবে উন্নত হয়।",
      "mr": "2026 मध्ये घर आणि कुटुंब केंद्रस्थानी असतात. मालमत्तेचे प्रश्न अनुकूलपणे सोडवले जातात. करिअरमध्ये स्थिर प्रगती होते आणि भावनिक कल्याण लक्षणीयरीत्या सुधारते.",
      "gu": "2026માં ઘર અને પરિવાર કેન્દ્રમાં રહે છે. મિલકતના મામલા અનુકૂળ રીતે ઉકેલાય છે. કારકિર્દીમાં સ્થિર પ્રગતિ જોવા મળે છે, અને ભાવનાત્મક સુખાકારીમાં નોંધપાત્ર સુધારો થાય છે.",
      "kn": "2026ರಲ್ಲಿ ಮನೆ ಮತ್ತು ಕುಟುಂಬ ಕೇಂದ್ರ ಸ್ಥಾನದಲ್ಲಿರುತ್ತವೆ. ಆಸ್ತಿ ವಿಷಯಗಳು ಅನುಕೂಲಕರವಾಗಿ ಪರಿಹಾರವಾಗುತ್ತವೆ. ವೃತ್ತಿಯು ಸ್ಥಿರ ಪ್ರಗತಿಯನ್ನು ಕಾಣುತ್ತದೆ, ಮತ್ತು ಭಾವನಾತ್ಮಕ ಯೋಗಕ್ಷೇಮ ಗಮನಾರ್ಹವಾಗಿ ಸುಧಾರಿಸುತ್ತದೆ.",
      "ml": "2026-ൽ വീടും കുടുംബവും കേന്ദ്ര സ്ഥാനത്ത് നിൽക്കുന്നു. സ്വത്ത് കാര്യങ്ങൾ അനുകൂലമായി പരിഹരിക്കപ്പെടുന്നു. കരിയർ സ്ഥിരമായ പുരോഗതി കാണുന്നു, വൈകാരിക ക്ഷേമം ഗണ്യമായി മെച്ചപ്പെടുന്നു.",
      "pa": "2026 ਵਿੱਚ ਘਰ ਅਤੇ ਪਰਿਵਾਰ ਕੇਂਦਰ ਵਿੱਚ ਰਹਿੰਦੇ ਹਨ। ਜਾਇਦਾਦ ਦੇ ਮਾਮਲੇ ਅਨੁਕੂਲ ਤਰੀਕੇ ਨਾਲ ਹੱਲ ਹੁੰਦੇ ਹਨ। ਕਰੀਅਰ ਸਥਿਰ ਤਰੱਕੀ ਦੇਖਦਾ ਹੈ, ਅਤੇ ਭਾਵਨਾਤਮਕ ਤੰਦਰੁਸਤੀ ਵਿੱਚ ਕਾਫ਼ੀ ਸੁਧਾਰ ਹੁੰਦਾ ਹੈ।"
    },
    "horoscope.2026.zodiac.cancer.highlight1": {
      "en": "Property acquisition favorable",
      "hi": "संपत्ति अधिग्रहण अनुकूल",
      "ta": "சொத்து கையகப்படுத்துதல் சாதகமானது",
      "te": "ఆస్తి సేకరణ అనుకూలం",
      "bn": "সম্পত্তি অধিগ্রহণ অনুকূল",
      "mr": "मालमत्ता संपादन अनुकूल",
      "gu": "મિલકત સંપાદન અનુકૂળ",
      "kn": "ಆಸ್ತಿ ಸ್ವಾಧೀನ ಅನುಕೂಲಕರ",
      "ml": "സ്വത്ത് ഏറ്റെടുക്കൽ അനുകൂലം",
      "pa": "ਜਾਇਦਾਦ ਪ੍ਰਾਪਤੀ ਅਨੁਕੂਲ"
    },
    "horoscope.2026.zodiac.cancer.highlight2": {
      "en": "Family harmony improves",
      "hi": "पारिवारिक सामंजस्य में सुधार",
      "ta": "குடும்ப ஒற்றுமை மேம்படுகிறது",
      "te": "కుటుంబ సామరస్యం మెరుగుపడుతుంది",
      "bn": "পারিবারিক সম্প্রীতি উন্নত হয়",
      "mr": "कौटुंबिक सुसंवाद सुधारतो",
      "gu": "કૌટુંબિક સંવાદિતા સુધરે છે",
      "kn": "ಕುಟುಂಬ ಸಾಮರಸ್ಯ ಸುಧಾರಿಸುತ್ತದೆ",
      "ml": "കുടുംബ ഐക്യം മെച്ചപ്പെടുന്നു",
      "pa": "ਪਰਿਵਾਰਕ ਸਦਭਾਵਨਾ ਵਿੱਚ ਸੁਧਾਰ"
    },
    "horoscope.2026.zodiac.cancer.highlight3": {
      "en": "Emotional healing journey",
      "hi": "भावनात्मक उपचार की यात्रा",
      "ta": "உணர்ச்சி குணமாகும் பயணம்",
      "te": "భావోద్వేగ నయం ప్రయాణం",
      "bn": "মানসিক নিরাময় যাত্রা",
      "mr": "भावनिक उपचार प्रवास",
      "gu": "ભાવનાત્મક ઉપચાર યાત્રા",
      "kn": "ಭಾವನಾತ್ಮಕ ಗುಣಪಡಿಸುವ ಪ್ರಯಾಣ",
      "ml": "വൈകാരിക രോഗശാന്തി യാത്ര",
      "pa": "ਭਾਵਨਾਤਮਕ ਇਲਾਜ ਯਾਤਰਾ"
    }
  }
}
