{
  "section": "doshas",
  "keys": {
    "pitraDosh.title": {
      "en": "Pitra Dosh (Pitru Dosha)",
      "hi": "पितृ दोष (पितृ दोष)",
      "ta": "பித்ரு தோஷம் (பித்ரு தோஷம்)",
      "te": "పితృ దోషం (పితృ దోషం)",
      "bn": "পিতৃ দোষ (পিতৃ দোষ)",
      "mr": "पितृ दोष (पितृ दोष)",
      "gu": "પિતૃ દોષ (પિતૃ દોષ)",
      "kn": "ಪಿತೃ ದೋಷ (ಪಿತೃ ದೋಷ)",
      "ml": "പിതൃ ദോഷം (പിതൃ ദോഷം)",
      "pa": "ਪਿਤਰ ਦੋਸ਼ (ਪਿਤਰ ਦੋਸ਼)"
    },
    "pitraDosh.subtitle": {
      "en": "Complete guide to understanding Pitra Dosh, ancestral karma, its effects on family and life, and powerful remedies to honor and pacify ancestors.",
      "hi": "पितृ दोष, पूर्वजों के कर्म, परिवार और जीवन पर इसके प्रभाव, और पूर्वजों को सम्मान देने और शांत करने के शक्तिशाली उपायों को समझने के लिए संपूर्ण मार्गदर्शिका।",
      "ta": "பித்ரு தோஷம், மூதாதையர் கர்மா, குடும்பம் மற்றும் வாழ்க்கையில் அதன் விளைவுகள், மற்றும் மூதாதையர்களை கௌரவிக்கவும் சமாதானப்படுத்தவும் சக்திவாய்ந்த பரிகாரங்களை புரிந்துகொள்ள முழுமையான வழிகாட்டி.",
      "te": "పితృ దోషం, పూర్వీకుల కర్మ, కుటుంబం మరియు జీవితంపై దాని ప్రభావాలు, మరియు పూర్వీకులను గౌరవించడానికి మరియు శాంతింపజేయడానికి శక్తివంతమైన పరిహారాలను అర్థం చేసుకోవడానికి సంపూర్ణ మార్గదర్శి.",
      "bn": "পিতৃ দোষ, পূর্বপুরুষদের কর্ম, পরিবার ও জীবনে এর প্রভাব এবং পূর্বপুরুষদের সম্মান ও শান্ত করার শক্তিশালী প্রতিকার বোঝার সম্পূর্ণ গাইড।",
      "mr": "पितृ दोष, पूर्वजांचे कर्म, कुटुंब आणि जीवनावर त्याचे परिणाम आणि पूर्वजांचा सन्मान करण्यासाठी आणि शांत करण्यासाठी शक्तिशाली उपाय समजून घेण्यासाठी संपूर्ण मार्गदर्शक।",
      "gu": "પિતૃ દોષ, પૂર્વજોના કર્મ, કુટુંબ અને જીવન પર તેની અસરો અને પૂર્વજોનું સન્માન કરવા અને શાંત કરવા માટે શક્તિશાળી ઉપાયો સમજવા માટે સંપૂર્ણ માર્ગદર્શિકા.",
      "kn": "ಪಿತೃ ದೋಷ, ಪೂರ್ವಜರ ಕರ್ಮ, ಕುಟುಂಬ ಮತ್ತು ಜೀವನದ ಮೇಲೆ ಅದರ ಪರಿಣಾಮಗಳು ಮತ್ತು ಪೂರ್ವಜರನ್ನು ಗೌರವಿಸಲು ಮತ್ತು ಶಾಂತಗೊಳಿಸಲು ಶಕ್ತಿಶಾಲಿ ಪರಿಹಾರಗಳನ್ನು ಅರ್ಥಮಾಡಿಕೊಳ್ಳಲು ಸಂಪೂರ್ಣ ಮಾರ್ಗದರ್ಶಿ.",
      "ml": "പിതൃ ദോഷം, പൂർവ്വികരുടെ കർമ്മം, കുടുംബത്തിലും ജീവിതത്തിലും അതിന്റെ ഫലങ്ങൾ, പൂർവ്വികരെ ബഹുമാനിക്കാനും ശാന്തമാക്കാനും ശക്തമായ പരിഹാരങ്ങൾ മനസ്സിലാക്കാനുള്ള സമ്പൂർണ്ണ ഗൈഡ്.",
      "pa": "ਪਿਤਰ ਦੋਸ਼, ਪੂਰਵਜਾਂ ਦੇ ਕਰਮ, ਪਰਿਵਾਰ ਅਤੇ ਜੀਵਨ 'ਤੇ ਇਸਦੇ ਪ੍ਰਭਾਵਾਂ, ਅਤੇ ਪੂਰਵਜਾਂ ਦਾ ਸਨਮਾਨ ਕਰਨ ਅਤੇ ਸ਼ਾਂਤ ਕਰਨ ਲਈ ਸ਼ਕਤੀਸ਼ਾਲੀ ਉਪਾਵਾਂ ਨੂੰ ਸਮਝਣ ਲਈ ਸੰਪੂਰਨ ਗਾਈਡ।"
    },
    "pitraDosh.ancestralKarma": {
      "en": "Ancestral Karma",
      "hi": "पूर्वजों का कर्म",
      "ta": "மூதாதையர் கர்மா",
      "te": "పూర్వీకుల కర్మ",
      "bn": "পূর্বপুরুষদের কর্ম",
      "mr": "पूर्वजांचे कर्म",
      "gu": "પૂર્વજોનું કર્મ",
      "kn": "ಪೂರ್ವಜರ ಕರ್ಮ",
      "ml": "പൂർവ്വികരുടെ കർമ്മം",
      "pa": "ਪੂਰਵਜਾਂ ਦਾ ਕਰਮ"
    },
    "pitraDosh.whatIs.title": {
      "en": "What is Pitra Dosh?",
      "hi": "पितृ दोष क्या है?",
      "ta": "பித்ரு தோஷம் என்றால் என்ன?",
      "te": "పితృ దోషం అంటే ఏమిటి?",
      "bn": "পিতৃ দোষ কী?",
      "mr": "पितृ दोष म्हणजे काय?",
      "gu": "પિતૃ દોષ શું છે?",
      "kn": "ಪಿತೃ ದೋಷ ಎಂದರೇನು?",
      "ml": "പിതൃ ദോഷം എന്താണ്?",
      "pa": "ਪਿਤਰ ਦੋਸ਼ ਕੀ ਹੈ?"
    },
    "pitraDosh.whatIs.description1": {
      "en": "Pitra Dosh (also spelled Pitru Dosha) is a karmic debt owed to ancestors. In Vedic astrology, it occurs when the souls of departed ancestors are unsatisfied due to various reasons, and their unfulfilled karma affects the current generation.",
      "hi": "पितृ दोष पूर्वजों के प्रति एक कर्म ऋण है। वैदिक ज्योतिष में, यह तब होता है जब दिवंगत पूर्वजों की आत्माएं विभिन्न कारणों से असंतुष्ट होती हैं, और उनका अधूरा कर्म वर्तमान पीढ़ी को प्रभावित करता है।",
      "ta": "பித்ரு தோஷம் மூதாதையர்களுக்கு செலுத்த வேண்டிய கர்ம கடன். வேத ஜோதிடத்தில், இறந்த மூதாதையர்களின் ஆன்மாக்கள் பல்வேறு காரணங்களால் திருப்தியடையாதபோது இது நிகழ்கிறது, மேலும் அவர்களின் நிறைவேறாத கர்மா தற்போதைய தலைமுறையை பாதிக்கிறது.",
      "te": "పితృ దోషం పూర్వీకులకు చెల్లించవలసిన కర్మ రుణం. వేద జ్యోతిషంలో, మరణించిన పూర్వీకుల ఆత్మలు వివిధ కారణాల వల్ల అసంతృప్తిగా ఉన్నప్పుడు ఇది సంభవిస్తుంది, మరియు వారి అసంపూర్ణ కర్మ ప్రస్తుత తరాన్ని ప్రభావితం చేస్తుంది.",
      "bn": "পিতৃ দোষ পূর্বপুরুষদের প্রতি একটি কর্ম ঋণ। বৈদিক জ্যোতিষে, এটি ঘটে যখন প্রয়াত পূর্বপুরুষদের আত্মা বিভিন্ন কারণে অসন্তুষ্ট থাকে এবং তাদের অপূর্ণ কর্ম বর্তমান প্রজন্মকে প্রভাবিত করে।",
      "mr": "पितृ दोष हे पूर्वजांप्रती असलेले कर्म ऋण आहे। वैदिक ज्योतिषात, जेव्हा दिवंगत पूर्वजांचे आत्मे विविध कारणांमुळे असंतुष्ट असतात आणि त्यांचे अपूर्ण कर्म सध्याच्या पिढीवर परिणाम करते तेव्हा हे घडते.",
      "gu": "પિતૃ દોષ પૂર્વજો પ્રત્યેનું કર્મ ઋણ છે. વૈદિક જ્યોતિષમાં, જ્યારે દિવંગત પૂર્વજોની આત્માઓ વિવિધ કારણોસર અસંતુષ્ટ હોય છે અને તેમનું અધૂરું કર્મ વર્તમાન પેઢીને અસર કરે છે ત્યારે આ થાય છે.",
      "kn": "ಪಿತೃ ದೋಷವು ಪೂರ್ವಜರಿಗೆ ಸಲ್ಲಬೇಕಾದ ಕರ್ಮ ಋಣ. ವೈದಿಕ ಜ್ಯೋತಿಷ್ಯದಲ್ಲಿ, ಮರಣಹೊಂದಿದ ಪೂರ್ವಜರ ಆತ್ಮಗಳು ವಿವಿಧ ಕಾರಣಗಳಿಂದ ಅತೃಪ್ತರಾದಾಗ ಮತ್ತು ಅವರ ಅಪೂರ್ಣ ಕರ್ಮವು ಪ್ರಸ್ತುತ ಪೀಳಿಗೆಯ ಮೇಲೆ ಪರಿಣಾಮ ಬೀರಿದಾಗ ಇದು ಸಂಭವಿಸುತ್ತದೆ.",
      "ml": "പിതൃ ദോഷം പൂർവ്വികർക്ക് നൽകേണ്ട കർമ്മ കടമാണ്. വേദ ജ്യോതിഷത്തിൽ, മരിച്ച പൂർവ്വികരുടെ ആത്മാക്കൾ വിവിധ കാരണങ്ങളാൽ അസംതൃപ്തരാകുമ്പോഴും അവരുടെ പൂർത്തിയാകാത്ത കർമ്മം ഇപ്പോഴത്തെ തലമുറയെ ബാധിക്കുമ്പോഴും ഇത് സംഭവിക്കുന്നു.",
      "pa": "ਪਿਤਰ ਦੋਸ਼ ਪੂਰਵਜਾਂ ਪ੍ਰਤੀ ਇੱਕ ਕਰਮ ਕਰਜ਼ਾ ਹੈ। ਵੈਦਿਕ ਜੋਤਿਸ਼ ਵਿੱਚ, ਇਹ ਉਦੋਂ ਹੁੰਦਾ ਹੈ ਜਦੋਂ ਮਰਹੂਮ ਪੂਰਵਜਾਂ ਦੀਆਂ ਆਤਮਾਵਾਂ ਵੱਖ-ਵੱਖ ਕਾਰਨਾਂ ਕਰਕੇ ਅਸੰਤੁਸ਼ਟ ਹੁੰਦੀਆਂ ਹਨ, ਅਤੇ ਉਨ੍ਹਾਂ ਦਾ ਅਧੂਰਾ ਕਰਮ ਮੌਜੂਦਾ ਪੀੜ੍ਹੀ ਨੂੰ ਪ੍ਰਭਾਵਿਤ ਕਰਦਾ ਹੈ।"
    },
    "pitraDosh.whatIs.description2": {
      "en": "The word \"Pitra\" means ancestors or forefathers, and \"Dosh\" means affliction or fault. This dosha is identified in the birth chart primarily through the position of the Sun (representing father and ancestors), the 9th house (house of father and fortune), and the nodes Rahu and Ketu.",
      "hi": "\"पितृ\" शब्द का अर्थ है पूर्वज या पितामह, और \"दोष\" का अर्थ है कष्ट या दोष। इस दोष की पहचान जन्म कुंडली में मुख्य रूप से सूर्य (पिता और पूर्वजों का प्रतिनिधित्व), 9वें भाव (पिता और भाग्य का भाव), और राहु-केतु की स्थिति से होती है।",
      "ta": "\"பித்ரு\" என்ற சொல் மூதாதையர்கள் அல்லது முன்னோர்களைக் குறிக்கிறது, \"தோஷம்\" என்றால் துன்பம் அல்லது குறை. இந்த தோஷம் ஜாதகத்தில் முக்கியமாக சூரியன் (தந்தை மற்றும் மூதாதையர்களைக் குறிக்கும்), 9வது வீடு (தந்தை மற்றும் அதிர்ஷ்டத்தின் வீடு), மற்றும் ராகு கேது மூலம் அடையாளம் காணப்படுகிறது.",
      "te": "\"పితృ\" అనే పదానికి పూర్వీకులు లేదా తాతముత్తాతలు అని అర్థం, \"దోషం\" అంటే బాధ లేదా లోపం. ఈ దోషం జన్మ చార్ట్‌లో ప్రధానంగా సూర్యుడు (తండ్రి మరియు పూర్వీకులను సూచిస్తుంది), 9వ భావం (తండ్రి మరియు అదృష్టం యొక్క భావం), మరియు రాహు కేతు స్థానం ద్వారా గుర్తించబడుతుంది.",
      "bn": "\"পিতৃ\" শব্দের অর্থ পূর্বপুরুষ বা পিতামহ, এবং \"দোষ\" মানে কষ্ট বা ত্রুটি। এই দোষ জন্ম কুণ্ডলীতে প্রধানত সূর্য (পিতা ও পূর্বপুরুষদের প্রতিনিধিত্ব করে), 9ম ভাব (পিতা ও ভাগ্যের ভাব), এবং রাহু-কেতুর অবস্থান দ্বারা চিহ্নিত হয়।",
      "mr": "\"पितृ\" या शब्दाचा अर्थ पूर्वज किंवा वडिलोपार्जित, आणि \"दोष\" म्हणजे त्रास किंवा दोष. हा दोष जन्म कुंडलीत प्रामुख्याने सूर्य (वडील आणि पूर्वजांचे प्रतिनिधित्व), 9वे घर (वडील आणि नशिबाचे घर), आणि राहू-केतूच्या स्थितीद्वारे ओळखला जातो.",
      "gu": "\"પિતૃ\" શબ્દનો અર્થ પૂર્વજો અથવા પિતામહ છે, અને \"દોષ\" નો અર્થ કષ્ટ અથવા ખામી છે. આ દોષ જન્મ કુંડળીમાં મુખ્યત્વે સૂર્ય (પિતા અને પૂર્વજોનું પ્રતિનિધિત્વ), 9મું ઘર (પિતા અને નસીબનું ઘર), અને રાહુ-કેતુની સ્થિતિ દ્વારા ઓળખાય છે.",
      "kn": "\"ಪಿತೃ\" ಎಂಬ ಪದವು ಪೂರ್ವಜರು ಅಥವಾ ಪಿತಾಮಹರು ಎಂದರ್ಥ, ಮತ್ತು \"ದೋಷ\" ಎಂದರೆ ಕಷ್ಟ ಅಥವಾ ದೋಷ. ಈ ದೋಷವನ್ನು ಜನ್ಮ ಕುಂಡಲಿಯಲ್ಲಿ ಮುಖ್ಯವಾಗಿ ಸೂರ್ಯ (ತಂದೆ ಮತ್ತು ಪೂರ್ವಜರನ್ನು ಪ್ರತಿನಿಧಿಸುತ್ತದೆ), 9ನೇ ಮನೆ (ತಂದೆ ಮತ್ತು ಅದೃಷ್ಟದ ಮನೆ), ಮತ್ತು ರಾಹು-ಕೇತುವಿನ ಸ್ಥಾನದ ಮೂಲಕ ಗುರುತಿಸಲಾಗುತ್ತದೆ.",
      "ml": "\"പിതൃ\" എന്ന വാക്കിന്റെ അർത്ഥം പൂർവ്വികർ അല്ലെങ്കിൽ പിതാമഹന്മാർ എന്നാണ്, \"ദോഷം\" എന്നാൽ കഷ്ടം അല്ലെങ്കിൽ കുറവ് എന്നാണ്. ഈ ദോഷം ജനന ചാർട്ടിൽ പ്രധാനമായും സൂര്യൻ (പിതാവിനെയും പൂർവ്വികരെയും പ്രതിനിധീകരിക്കുന്നു), 9-ാം ഭാവം (പിതാവിന്റെയും ഭാഗ്യത്തിന്റെയും ഭാവം), രാഹു-കേതുവിന്റെ സ്ഥാനം എന്നിവയിലൂടെ തിരിച്ചറിയുന്നു.",
      "pa": "\"ਪਿਤਰ\" ਸ਼ਬਦ ਦਾ ਅਰਥ ਹੈ ਪੂਰਵਜ ਜਾਂ ਦਾਦਾ-ਪੜਦਾਦਾ, ਅਤੇ \"ਦੋਸ਼\" ਦਾ ਅਰਥ ਹੈ ਕਸ਼ਟ ਜਾਂ ਨੁਕਸ। ਇਹ ਦੋਸ਼ ਜਨਮ ਕੁੰਡਲੀ ਵਿੱਚ ਮੁੱਖ ਤੌਰ 'ਤੇ ਸੂਰਜ (ਪਿਤਾ ਅਤੇ ਪੂਰਵਜਾਂ ਦੀ ਨੁਮਾਇੰਦਗੀ), 9ਵੇਂ ਘਰ (ਪਿਤਾ ਅਤੇ ਕਿਸਮਤ ਦਾ ਘਰ), ਅਤੇ ਰਾਹੂ-ਕੇਤੂ ਦੀ ਸਥਿਤੀ ਦੁਆਰਾ ਪਛਾਣਿਆ ਜਾਂਦਾ ਹੈ।"
    },
    "pitraDosh.whatIs.description3": {
      "en": "Pitra Dosh is not a curse but rather unresolved ancestral karma that needs to be addressed through proper rituals, worship, and good deeds. By honoring our ancestors and performing prescribed remedies, we can help their souls find peace and remove obstacles from our own lives.",
      "hi": "पितृ दोष कोई श्राप नहीं है बल्कि अनसुलझा पूर्वजों का कर्म है जिसे उचित अनुष्ठानों, पूजा और अच्छे कर्मों के माध्यम से संबोधित करने की आवश्यकता है। अपने पूर्वजों का सम्मान करके और निर्धारित उपाय करके, हम उनकी आत्माओं को शांति पाने में मदद कर सकते हैं और अपने जीवन से बाधाओं को दूर कर सकते हैं।",
      "ta": "பித்ரு தோஷம் ஒரு சாபம் அல்ல, மாறாக சரியான சடங்குகள், வழிபாடு மற்றும் நல்ல செயல்கள் மூலம் தீர்க்கப்பட வேண்டிய தீர்க்கப்படாத மூதாதையர் கர்மா. நமது மூதாதையர்களை கௌரவித்து, பரிந்துரைக்கப்பட்ட பரிகாரங்களைச் செய்வதன் மூலம், அவர்களின் ஆன்மாக்கள் அமைதி பெற உதவலாம் மற்றும் நம் சொந்த வாழ்க்கையிலிருந்து தடைகளை நீக்கலாம்.",
      "te": "పితృ దోషం శాపం కాదు, సరైన ఆచారాలు, పూజ మరియు మంచి పనుల ద్వారా పరిష్కరించవలసిన పరిష్కరించని పూర్వీకుల కర్మ. మన పూర్వీకులను గౌరవించడం మరియు నిర్దేశించిన పరిహారాలు చేయడం ద్వారా, వారి ఆత్మలకు శాంతి లభించడానికి మరియు మన స్వంత జీవితాల నుండి అడ్డంకులను తొలగించడానికి మనం సహాయపడగలము.",
      "bn": "পিতৃ দোষ কোনো অভিশাপ নয় বরং অমীমাংসিত পূর্বপুরুষদের কর্ম যা সঠিক আচার-অনুষ্ঠান, পূজা এবং ভালো কাজের মাধ্যমে সমাধান করা প্রয়োজন। আমাদের পূর্বপুরুষদের সম্মান করে এবং নির্ধারিত প্রতিকার করে, আমরা তাদের আত্মাকে শান্তি পেতে সাহায্য করতে পারি এবং আমাদের নিজেদের জীবন থেকে বাধা দূর করতে পারি।",
      "mr": "पितृ दोष हा शाप नाही तर योग्य विधी, पूजा आणि चांगल्या कर्मांद्वारे सोडवणे आवश्यक असलेले अनिराकृत पूर्वजांचे कर्म आहे. आपल्या पूर्वजांचा सन्मान करून आणि निर्धारित उपाय करून, आपण त्यांच्या आत्म्यांना शांती मिळवून देण्यास आणि आपल्या स्वतःच्या जीवनातून अडथळे दूर करण्यास मदत करू शकतो.",
      "gu": "પિતૃ દોષ કોઈ શ્રાપ નથી પરંતુ યોગ્ય વિધિઓ, પૂજા અને સારા કાર્યો દ્વારા ઉકેલવા જરૂરી અનિરાકૃત પૂર્વજોનું કર્મ છે. આપણા પૂર્વજોનું સન્માન કરીને અને નિર્ધારિત ઉપાયો કરીને, આપણે તેમની આત્માઓને શાંતિ મેળવવામાં મદદ કરી શકીએ છીએ અને આપણા પોતાના જીવનમાંથી અવરોધો દૂર કરી શકીએ છીએ.",
      "kn": "ಪಿತೃ ದೋಷವು ಶಾಪವಲ್ಲ ಆದರೆ ಸರಿಯಾದ ಆಚರಣೆಗಳು, ಪೂಜೆ ಮತ್ತು ಒಳ್ಳೆಯ ಕಾರ್ಯಗಳ ಮೂಲಕ ಪರಿಹರಿಸಬೇಕಾದ ಪರಿಹರಿಸದ ಪೂರ್ವಜರ ಕರ್ಮ. ನಮ್ಮ ಪೂರ್ವಜರನ್ನು ಗೌರವಿಸುವ ಮೂಲಕ ಮತ್ತು ನಿಗದಿತ ಪರಿಹಾರಗಳನ್ನು ಮಾಡುವ ಮೂಲಕ, ಅವರ ಆತ್ಮಗಳಿಗೆ ಶಾಂತಿ ಸಿಗಲು ಸಹಾಯ ಮಾಡಬಹುದು ಮತ್ತು ನಮ್ಮ ಸ್ವಂತ ಜೀವನದಿಂದ ಅಡೆತಡೆಗಳನ್ನು ತೆಗೆದುಹಾಕಬಹುದು.",
      "ml": "പിതൃ ദോഷം ഒരു ശാപമല്ല, മറിച്ച് ശരിയായ ആചാരങ്ങൾ, ആരാധന, നല്ല പ്രവൃത്തികൾ എന്നിവയിലൂടെ പരിഹരിക്കേണ്ട പരിഹരിക്കാത്ത പൂർവ്വിക കർമ്മമാണ്. നമ്മുടെ പൂർവ്വികരെ ബഹുമാനിച്ചും നിർദ്ദേശിച്ച പരിഹാരങ്ങൾ ചെയ്തും, അവരുടെ ആത്മാക്കൾക്ക് സമാധാനം കണ്ടെത്താനും നമ്മുടെ സ്വന്തം ജീവിതത്തിൽ നിന്ന് തടസ്സങ്ങൾ നീക്കം ചെയ്യാനും നമുക്ക് സഹായിക്കാനാകും.",
      "pa": "ਪਿਤਰ ਦੋਸ਼ ਕੋਈ ਸਰਾਪ ਨਹੀਂ ਹੈ ਬਲਕਿ ਅਣਸੁਲਝਿਆ ਪੂਰਵਜਾਂ ਦਾ ਕਰਮ ਹੈ ਜਿਸ ਨੂੰ ਸਹੀ ਰੀਤੀ-ਰਿਵਾਜਾਂ, ਪੂਜਾ ਅਤੇ ਚੰਗੇ ਕੰਮਾਂ ਰਾਹੀਂ ਹੱਲ ਕਰਨ ਦੀ ਲੋੜ ਹੈ। ਆਪਣੇ ਪੂਰਵਜਾਂ ਦਾ ਸਨਮਾਨ ਕਰਕੇ ਅਤੇ ਨਿਰਧਾਰਤ ਉਪਾਅ ਕਰਕੇ, ਅਸੀਂ ਉਨ੍ਹਾਂ ਦੀਆਂ ਆਤਮਾਵਾਂ ਨੂੰ ਸ਼ਾਂਤੀ ਪ੍ਰਾਪਤ ਕਰਨ ਵਿੱਚ ਮਦਦ ਕਰ ਸਕਦੇ ਹਾਂ ਅਤੇ ਆਪਣੀ ਜ਼ਿੰਦਗੀ ਤੋਂ ਰੁਕਾਵਟਾਂ ਦੂਰ ਕਰ ਸਕਦੇ ਹਾਂ।"
    }
  }
}
