{
  "section": "transits",
  "keys": {
    "transits.saturn.signs.aries.name": {
      "en": "Aries",
      "hi": "मेष",
      "ta": "மேஷம்",
      "te": "మేషం",
      "bn": "মেষ",
      "mr": "मेष",
      "gu": "મેષ",
      "kn": "ಮೇಷ",
      "ml": "മേടം",
      "pa": "ਮੇਖ"
    },
    "transits.saturn.signs.aries.hindi": {
      "en": "Mesha",
      "hi": "मेष",
      "ta": "மேஷம்",
      "te": "మేషం",
      "bn": "মেষ",
      "mr": "मेष",
      "gu": "મેષ",
      "kn": "ಮೇಷ",
      "ml": "മേടം",
      "pa": "ਮੇਖ"
    },
    "transits.saturn.signs.aries.house": {
      "en": "12th House",
      "hi": "12वां भाव",
      "ta": "12வது வீடு",
      "te": "12వ భావం",
      "bn": "12তম ভাব",
      "mr": "12वे स्थान",
      "gu": "12મું ઘર",
      "kn": "12ನೇ ಮನೆ",
      "ml": "12-ാം ഭാവം",
      "pa": "12ਵਾਂ ਘਰ"
    },
    "transits.saturn.signs.aries.effect": {
      "en": "Challenging",
      "hi": "चुनौतीपूर्ण",
      "ta": "சவாலான",
      "te": "సవాలు",
      "bn": "চ্যালেঞ্জিং",
      "mr": "आव्हानात्मक",
      "gu": "પડકારજનક",
      "kn": "ಸವಾಲಿನ",
      "ml": "വെല്ലുവിളി",
      "pa": "ਚੁਣੌਤੀਪੂਰਨ"
    },
    "transits.saturn.signs.aries.description": {
      "en": "Saturn transits your 12th house of losses, expenses, and spirituality. This period encourages spiritual growth but may bring increased expenses and sleep issues. Foreign connections are highlighted.",
      "hi": "शनि आपके 12वें भाव में गोचर करता है जो हानि, खर्च और आध्यात्मिकता का है। यह अवधि आध्यात्मिक विकास को प्रोत्साहित करती है लेकिन बढ़े हुए खर्च और नींद की समस्याएं ला सकती है। विदेशी संबंध उजागर होते हैं।",
      "ta": "சனி உங்கள் 12வது வீட்டில் பயணிக்கிறது, இது இழப்புகள், செலவுகள் மற்றும் ஆன்மீகத்தின் வீடு. இந்த காலம் ஆன்மீக வளர்ச்சியை ஊக்குவிக்கிறது ஆனால் அதிகரித்த செலவுகள் மற்றும் தூக்க பிரச்சனைகளை கொண்டு வரலாம். வெளிநாட்டு தொடர்புகள் முன்னிலைப்படுத்தப்படுகின்றன.",
      "te": "శని మీ 12వ భావంలో సంచరిస్తుంది, ఇది నష్టాలు, ఖర్చులు మరియు ఆధ్యాత్మికత యొక్క భావం. ఈ కాలం ఆధ్యాత్మిక వృద్ధిని ప్రోత్సహిస్తుంది కానీ పెరిగిన ఖర్చులు మరియు నిద్ర సమస్యలను తీసుకురావచ్చు. విదేశీ సంబంధాలు హైలైట్ చేయబడతాయి.",
      "bn": "শনি আপনার 12তম ভাবে গোচর করছে যা ক্ষতি, ব্যয় এবং আধ্যাত্মিকতার ভাব। এই সময়কাল আধ্যাত্মিক বৃদ্ধিকে উৎসাহিত করে কিন্তু বর্ধিত ব্যয় এবং ঘুমের সমস্যা আনতে পারে। বিদেশী সংযোগ হাইলাইট করা হয়।",
      "mr": "शनि तुमच्या 12व्या स्थानातून गोचर करतो जे हानी, खर्च आणि अध्यात्माचे स्थान आहे। हा काळ आध्यात्मिक वाढीस प्रोत्साहन देतो परंतु वाढलेला खर्च आणि झोपेच्या समस्या आणू शकतो. परदेशी संबंध अधोरेखित होतात.",
      "gu": "શનિ તમારા 12મા ઘરમાં ગોચર કરે છે જે નુકસાન, ખર્ચ અને આધ્યાત્મિકતાનું ઘર છે. આ સમયગાળો આધ્યાત્મિક વિકાસને પ્રોત્સાહિત કરે છે પરંતુ વધેલા ખર્ચ અને ઊંઘની સમસ્યાઓ લાવી શકે છે. વિદેશી જોડાણો પ્રકાશિત થાય છે.",
      "kn": "ಶನಿ ನಿಮ್ಮ 12ನೇ ಮನೆಯಲ್ಲಿ ಸಂಚರಿಸುತ್ತಿದೆ, ಇದು ನಷ್ಟಗಳು, ಖರ್ಚುಗಳು ಮತ್ತು ಆಧ್ಯಾತ್ಮಿಕತೆಯ ಮನೆ. ಈ ಅವಧಿಯು ಆಧ್ಯಾತ್ಮಿಕ ಬೆಳವಣಿಗೆಯನ್ನು ಪ್ರೋತ್ಸಾಹಿಸುತ್ತದೆ ಆದರೆ ಹೆಚ್ಚಿದ ಖರ್ಚುಗಳು ಮತ್ತು ನಿದ್ರೆ ಸಮಸ್ಯೆಗಳನ್ನು ತರಬಹುದು. ವಿದೇಶಿ ಸಂಪರ್ಕಗಳು ಹೈಲೈಟ್ ಆಗುತ್ತವೆ.",
      "ml": "ശനി നിങ്ങളുടെ 12-ാം ഭാവത്തിലൂടെ സഞ്ചരിക്കുന്നു, ഇത് നഷ്ടങ്ങൾ, ചെലവുകൾ, ആത്മീയതയുടെ ഭാവമാണ്. ഈ കാലഘട്ടം ആത്മീയ വളർച്ചയെ പ്രോത്സാഹിപ്പിക്കുന്നു എന്നാൽ വർദ്ധിച്ച ചെലവുകളും ഉറക്ക പ്രശ്നങ്ങളും കൊണ്ടുവന്നേക്കാം. വിദേശ ബന്ധങ്ങൾ ഹൈലൈറ്റ് ചെയ്യപ്പെടുന്നു.",
      "pa": "ਸ਼ਨੀ ਤੁਹਾਡੇ 12ਵੇਂ ਘਰ ਵਿੱਚ ਗੋਚਰ ਕਰ ਰਿਹਾ ਹੈ ਜੋ ਨੁਕਸਾਨ, ਖਰਚੇ ਅਤੇ ਅਧਿਆਤਮਿਕਤਾ ਦਾ ਘਰ ਹੈ। ਇਹ ਸਮਾਂ ਅਧਿਆਤਮਿਕ ਵਿਕਾਸ ਨੂੰ ਉਤਸ਼ਾਹਿਤ ਕਰਦਾ ਹੈ ਪਰ ਵਧੇ ਹੋਏ ਖਰਚੇ ਅਤੇ ਨੀਂਦ ਦੀਆਂ ਸਮੱਸਿਆਵਾਂ ਲਿਆ ਸਕਦਾ ਹੈ। ਵਿਦੇਸ਼ੀ ਸੰਬੰਧ ਉਜਾਗਰ ਹੁੰਦੇ ਹਨ।"
    },
    "transits.saturn.signs.aries.advice": {
      "en": "Focus on spiritual practices, meditation, and charitable activities. Avoid unnecessary expenses and maintain healthy sleep habits.",
      "hi": "आध्यात्मिक अभ्यास, ध्यान और धर्मार्थ गतिविधियों पर ध्यान दें। अनावश्यक खर्चों से बचें और स्वस्थ नींद की आदतें बनाए रखें।",
      "ta": "ஆன்மீக நடைமுறைகள், தியானம் மற்றும் தொண்டு நடவடிக்கைகளில் கவனம் செலுத்துங்கள். தேவையற்ற செலவுகளைத் தவிர்த்து ஆரோக்கியமான தூக்க பழக்கங்களை பராமரிக்கவும்.",
      "te": "ఆధ్యాత్మిక అభ్యాసాలు, ధ్యానం మరియు దాతృత్వ కార్యకలాపాలపై దృష్టి పెట్టండి. అనవసరమైన ఖర్చులను నివారించండి మరియు ఆరోగ్యకరమైన నిద్ర అలవాట్లను కొనసాగించండి.",
      "bn": "আধ্যাত্মিক অনুশীলন, ধ্যান এবং দাতব্য কার্যকলাপে মনোযোগ দিন। অপ্রয়োজনীয় খরচ এড়িয়ে চলুন এবং স্বাস্থ্যকর ঘুমের অভ্যাস বজায় রাখুন।",
      "mr": "आध्यात्मिक साधना, ध्यान आणि धर्मादाय कार्यांवर लक्ष केंद्रित करा. अनावश्यक खर्च टाळा आणि निरोगी झोपेच्या सवयी राखा.",
      "gu": "આધ્યાત્મિક પ્રથાઓ, ધ્યાન અને દાનશીલ પ્રવૃત્તિઓ પર ધ્યાન કેન્દ્રિત કરો. બિનજરૂરી ખર્ચ ટાળો અને સ્વસ્થ ઊંઘની આદતો જાળવો.",
      "kn": "ಆಧ್ಯಾತ್ಮಿಕ ಅಭ್ಯಾಸಗಳು, ಧ್ಯಾನ ಮತ್ತು ದಾನ ಚಟುವಟಿಕೆಗಳ ಮೇಲೆ ಗಮನ ಕೇಂದ್ರೀಕರಿಸಿ. ಅನಗತ್ಯ ಖರ್ಚುಗಳನ್ನು ತಪ್ಪಿಸಿ ಮತ್ತು ಆರೋಗ್ಯಕರ ನಿದ್ರೆ ಅಭ್ಯಾಸಗಳನ್ನು ಕಾಪಾಡಿಕೊಳ್ಳಿ.",
      "ml": "ആത്മീയ അനുഷ്ഠാനങ്ങൾ, ധ്യാനം, ദാനധർമ്മ പ്രവർത്തനങ്ങൾ എന്നിവയിൽ ശ്രദ്ധ കേന്ദ്രീകരിക്കുക. അനാവശ്യ ചെലവുകൾ ഒഴിവാക്കുകയും ആരോഗ്യകരമായ ഉറക്ക ശീലങ്ങൾ നിലനിർത്തുകയും ചെയ്യുക.",
      "pa": "ਅਧਿਆਤਮਿਕ ਅਭਿਆਸਾਂ, ਧਿਆਨ ਅਤੇ ਦਾਨੀ ਗਤੀਵਿਧੀਆਂ 'ਤੇ ਧਿਆਨ ਕੇਂਦਰਿਤ ਕਰੋ। ਬੇਲੋੜੇ ਖਰਚਿਆਂ ਤੋਂ ਬਚੋ ਅਤੇ ਸਿਹਤਮੰਦ ਨੀਂਦ ਦੀਆਂ ਆਦਤਾਂ ਬਣਾਈ ਰੱਖੋ।"
    },
    "transits.saturn.signs.taurus.name": {
      "en": "Taurus",
      "hi": "वृषभ",
      "ta": "ரிஷபம்",
      "te": "వృషభం",
      "bn": "বৃষ",
      "mr": "वृषभ",
      "gu": "વૃષભ",
      "kn": "ವೃಷಭ",
      "ml": "ഇടവം",
      "pa": "ਬ੍ਰਿਸ਼ਭ"
    },
    "transits.saturn.signs.taurus.house": {
      "en": "11th House",
      "hi": "11वां भाव",
      "ta": "11வது வீடு",
      "te": "11వ భావం",
      "bn": "11তম ভাব",
      "mr": "11वे स्थान",
      "gu": "11મું ઘર",
      "kn": "11ನೇ ಮನೆ",
      "ml": "11-ാം ഭാവം",
      "pa": "11ਵਾਂ ਘਰ"
    },
    "transits.saturn.signs.taurus.effect": {
      "en": "Favorable",
      "hi": "अनुकूल",
      "ta": "சாதகமான",
      "te": "అనుకూలం",
      "bn": "অনুকূল",
      "mr": "अनुकूल",
      "gu": "અનુકૂળ",
      "kn": "ಅನುಕೂಲ",
      "ml": "അനുകൂലം",
      "pa": "ਅਨੁਕੂਲ"
    },
    "transits.saturn.signs.taurus.description": {
      "en": "Saturn blesses your 11th house of gains and friendships. This is an excellent period for achieving long-term goals, expanding social networks, and increasing income through persistent efforts.",
      "hi": "शनि आपके 11वें भाव को आशीर्वाद देता है जो लाभ और मित्रता का है। यह दीर्घकालिक लक्ष्यों को प्राप्त करने, सामाजिक नेटवर्क का विस्तार करने और निरंतर प्रयासों के माध्यम से आय बढ़ाने के लिए एक उत्कृष्ट अवधि है।",
      "ta": "சனி உங்கள் 11வது வீட்டை ஆசீர்வதிக்கிறது, இது லாபங்கள் மற்றும் நட்புகளின் வீடு. இது நீண்டகால இலக்குகளை அடைவதற்கும், சமூக வலைப்பின்னல்களை விரிவுபடுத்துவதற்கும், தொடர்ச்சியான முயற்சிகள் மூலம் வருமானத்தை அதிகரிப்பதற்கும் சிறந்த காலம்.",
      "te": "శని మీ 11వ భావాన్ని ఆశీర్వదిస్తుంది, ఇది లాభాలు మరియు స్నేహాల భావం. ఇది దీర్ఘకాలిక లక్ష్యాలను సాధించడానికి, సామాజిక నెట్‌వర్క్‌లను విస్తరించడానికి మరియు నిరంతర ప్రయత్నాల ద్వారా ఆదాయాన్ని పెంచడానికి అద్భుతమైన కాలం.",
      "bn": "শনি আপনার 11তম ভাবকে আশীর্বাদ করে যা লাভ এবং বন্ধুত্বের ভাব। এটি দীর্ঘমেয়াদী লক্ষ্য অর্জন, সামাজিক নেটওয়ার্ক প্রসারিত করা এবং অবিরাম প্রচেষ্টার মাধ্যমে আয় বাড়ানোর জন্য একটি চমৎকার সময়।",
      "mr": "शनि तुमच्या 11व्या स्थानाला आशीर्वाद देतो जे लाभ आणि मैत्रीचे स्थान आहे। हा दीर्घकालीन उद्दिष्टे साध्य करण्यासाठी, सामाजिक नेटवर्क वाढवण्यासाठी आणि सातत्यपूर्ण प्रयत्नांद्वारे उत्पन्न वाढवण्यासाठी उत्कृष्ट काळ आहे.",
      "gu": "શનિ તમારા 11મા ઘરને આશીર્વાદ આપે છે જે લાભ અને મિત્રતાનું ઘર છે. આ લાંબા ગાળાના લક્ષ્યો હાંસલ કરવા, સામાજિક નેટવર્ક વિસ્તારવા અને સતત પ્રયત્નો દ્વારા આવક વધારવા માટે ઉત્તમ સમયગાળો છે.",
      "kn": "ಶನಿ ನಿಮ್ಮ 11ನೇ ಮನೆಯನ್ನು ಆಶೀರ್ವದಿಸುತ್ತದೆ, ಇದು ಲಾಭಗಳು ಮತ್ತು ಸ್ನೇಹಗಳ ಮನೆ. ಇದು ದೀರ್ಘಾವಧಿ ಗುರಿಗಳನ್ನು ಸಾಧಿಸಲು, ಸಾಮಾಜಿಕ ಜಾಲಗಳನ್ನು ವಿಸ್ತರಿಸಲು ಮತ್ತು ನಿರಂತರ ಪ್ರಯತ್ನಗಳ ಮೂಲಕ ಆದಾಯವನ್ನು ಹೆಚ್ಚಿಸಲು ಅತ್ಯುತ್ತಮ ಅವಧಿ.",
      "ml": "ശനി നിങ്ങളുടെ 11-ാം ഭാവത്തെ അനുഗ്രഹിക്കുന്നു, ഇത് ലാഭങ്ങളുടെയും സൗഹൃദങ്ങളുടെയും ഭാവമാണ്. ഇത് ദീർഘകാല ലക്ഷ്യങ്ങൾ നേടുന്നതിനും സാമൂഹിക ശൃംഖലകൾ വിപുലീകരിക്കുന്നതിനും നിരന്തര പരിശ്രമങ്ങളിലൂടെ വരുമാനം വർദ്ധിപ്പിക്കുന്നതിനും മികച്ച കാലഘട്ടമാണ്.",
      "pa": "ਸ਼ਨੀ ਤੁਹਾਡੇ 11ਵੇਂ ਘਰ ਨੂੰ ਆਸ਼ੀਰਵਾਦ ਦਿੰਦਾ ਹੈ ਜੋ ਲਾਭ ਅਤੇ ਦੋਸਤੀ ਦਾ ਘਰ ਹੈ। ਇਹ ਲੰਬੇ ਸਮੇਂ ਦੇ ਟੀਚਿਆਂ ਨੂੰ ਪ੍ਰਾਪਤ ਕਰਨ, ਸਮਾਜਿਕ ਨੈੱਟਵਰਕ ਵਧਾਉਣ ਅਤੇ ਲਗਾਤਾਰ ਯਤਨਾਂ ਰਾਹੀਂ ਆਮਦਨ ਵਧਾਉਣ ਲਈ ਸ਼ਾਨਦਾਰ ਸਮਾਂ ਹੈ।"
    },
    "transits.saturn.signs.taurus.advice": {
      "en": "Network actively, pursue long-term goals, and invest in friendships. Your patience will be rewarded with material gains.",
      "hi": "सक्रिय रूप से नेटवर्क करें, दीर्घकालिक लक्ष्यों का पीछा करें और मित्रता में निवेश करें। आपके धैर्य को भौतिक लाभ से पुरस्कृत किया जाएगा।",
      "ta": "தீவிரமாக நெட்வொர்க் செய்யுங்கள், நீண்டகால இலக்குகளைத் தொடருங்கள், நட்புகளில் முதலீடு செய்யுங்கள். உங்கள் பொறுமை பொருள் ஆதாயங்களால் வெகுமதி பெறும்.",
      "te": "చురుకుగా నెట్‌వర్క్ చేయండి, దీర్ఘకాలిక లక్ష్యాలను అనుసరించండి మరియు స్నేహాలలో పెట్టుబడి పెట్టండి. మీ సహనానికి భౌతిక లాభాలతో బహుమతి లభిస్తుంది.",
      "bn": "সক্রিয়ভাবে নেটওয়ার্ক করুন, দীর্ঘমেয়াদী লক্ষ্য অনুসরণ করুন এবং বন্ধুত্বে বিনিয়োগ করুন। আপনার ধৈর্য বস্তুগত লাভে পুরস্কৃত হবে।",
      "mr": "सक्रियपणे नेटवर्क करा, दीर्घकालीन उद्दिष्टांचा पाठपुरावा करा आणि मैत्रीत गुंतवणूक करा. तुमच्या धैर्याला भौतिक लाभाने बक्षीस मिळेल.",
      "gu": "સક્રિય રીતે નેટવર્ક કરો, લાંબા ગાળાના લક્ષ્યોનો પીછો કરો અને મિત્રતામાં રોકાણ કરો. તમારી ધીરજને ભૌતિક લાભથી પુરસ્કાર મળશે.",
      "kn": "ಸಕ್ರಿಯವಾಗಿ ನೆಟ್‌ವರ್ಕ್ ಮಾಡಿ, ದೀರ್ಘಾವಧಿ ಗುರಿಗಳನ್ನು ಅನುಸರಿಸಿ ಮತ್ತು ಸ್ನೇಹಗಳಲ್ಲಿ ಹೂಡಿಕೆ ಮಾಡಿ. ನಿಮ್ಮ ತಾಳ್ಮೆಗೆ ಭೌತಿಕ ಲಾಭಗಳಿಂದ ಪ್ರತಿಫಲ ಸಿಗುತ್ತದೆ.",
      "ml": "സജീവമായി നെറ്റ്‌വർക്ക് ചെയ്യുക, ദീർഘകാല ലക്ഷ്യങ്ങൾ പിന്തുടരുക, സൗഹൃദങ്ങളിൽ നിക്ഷേപിക്കുക. നിങ്ങളുടെ ക്ഷമയ്ക്ക് ഭൗതിക നേട്ടങ്ങളാൽ പ്രതിഫലം ലഭിക്കും.",
      "pa": "ਸਰਗਰਮੀ ਨਾਲ ਨੈੱਟਵਰਕ ਕਰੋ, ਲੰਬੇ ਸਮੇਂ ਦੇ ਟੀਚਿਆਂ ਦਾ ਪਿੱਛਾ ਕਰੋ ਅਤੇ ਦੋਸਤੀ ਵਿੱਚ ਨਿਵੇਸ਼ ਕਰੋ। ਤੁਹਾਡੇ ਧੀਰਜ ਨੂੰ ਭੌਤਿਕ ਲਾਭਾਂ ਨਾਲ ਇਨਾਮ ਮਿਲੇਗਾ।"
    },
    "transits.saturn.signs.gemini.name": {
      "en": "Gemini",
      "hi": "मिथुन",
      "ta": "மிதுனம்",
      "te": "మిథునం",
      "bn": "মিথুন",
      "mr": "मिथुन",
      "gu": "મિથુન",
      "kn": "ಮಿಥುನ",
      "ml": "മിഥുനം",
      "pa": "ਮਿਥੁਨ"
    },
    "transits.saturn.signs.gemini.house": {
      "en": "10th House",
      "hi": "10वां भाव",
      "ta": "10வது வீடு",
      "te": "10వ భావం",
      "bn": "10তম ভাব",
      "mr": "10वे स्थान",
      "gu": "10મું ઘર",
      "kn": "10ನೇ ಮನೆ",
      "ml": "10-ാം ഭാവം",
      "pa": "10ਵਾਂ ਘਰ"
    },
    "transits.saturn.signs.gemini.effect": {
      "en": "Mixed",
      "hi": "मिश्रित",
      "ta": "கலப்பு",
      "te": "మిశ్రమం",
      "bn": "মিশ্র",
      "mr": "मिश्र",
      "gu": "મિશ્ર",
      "kn": "ಮಿಶ್ರ",
      "ml": "മിശ്രം",
      "pa": "ਮਿਸ਼ਰਤ"
    },
    "transits.saturn.signs.gemini.description": {
      "en": "Saturn transits your career house, bringing both challenges and opportunities. Hard work leads to recognition, but expect increased responsibilities. Authority figures play important roles.",
      "hi": "शनि आपके करियर भाव में गोचर करता है, चुनौतियां और अवसर दोनों लाता है। कड़ी मेहनत से मान्यता मिलती है, लेकिन बढ़ी हुई जिम्मेदारियों की उम्मीद करें। अधिकारी व्यक्ति महत्वपूर्ण भूमिका निभाते हैं।",
      "ta": "சனி உங்கள் தொழில் வீட்டில் பயணிக்கிறது, சவால்களையும் வாய்ப்புகளையும் கொண்டு வருகிறது. கடின உழைப்பு அங்கீகாரத்திற்கு வழிவகுக்கிறது, ஆனால் அதிகரித்த பொறுப்புகளை எதிர்பார்க்கவும். அதிகார நபர்கள் முக்கிய பங்கு வகிக்கின்றனர்.",
      "te": "శని మీ కెరీర్ భావంలో సంచరిస్తుంది, సవాళ్లు మరియు అవకాశాలు రెండింటినీ తీసుకువస్తుంది. కష్టపడి పని చేయడం గుర్తింపుకు దారితీస్తుంది, కానీ పెరిగిన బాధ్యతలను ఆశించండి. అధికార వ్యక్తులు ముఖ్యమైన పాత్రలు పోషిస్తారు.",
      "bn": "শনি আপনার ক্যারিয়ার ভাবে গোচর করছে, চ্যালেঞ্জ এবং সুযোগ উভয়ই নিয়ে আসছে। কঠোর পরিশ্রম স্বীকৃতির দিকে নিয়ে যায়, কিন্তু বর্ধিত দায়িত্ব আশা করুন। কর্তৃত্বের ব্যক্তিরা গুরুত্বপূর্ণ ভূমিকা পালন করে।",
      "mr": "शनि तुमच्या करिअर स्थानातून गोचर करतो, आव्हाने आणि संधी दोन्ही आणतो. कठोर परिश्रमामुळे मान्यता मिळते, परंतु वाढलेल्या जबाबदाऱ्यांची अपेक्षा करा. अधिकारी व्यक्ती महत्त्वाची भूमिका बजावतात.",
      "gu": "શનિ તમારા કારકિર્દી ઘરમાં ગોચર કરે છે, પડકારો અને તકો બંને લાવે છે. સખત મહેનત માન્યતા તરફ દોરી જાય છે, પરંતુ વધેલી જવાબદારીઓની અપેક્ષા રાખો. સત્તાધીશ વ્યક્તિઓ મહત્વપૂર્ણ ભૂમિકા ભજવે છે.",
      "kn": "ಶನಿ ನಿಮ್ಮ ವೃತ್ತಿ ಮನೆಯಲ್ಲಿ ಸಂಚರಿಸುತ್ತಿದೆ, ಸವಾಲುಗಳು ಮತ್ತು ಅವಕಾಶಗಳೆರಡನ್ನೂ ತರುತ್ತಿದೆ. ಕಠಿಣ ಪರಿಶ್ರಮವು ಗುರುತಿಸುವಿಕೆಗೆ ಕಾರಣವಾಗುತ್ತದೆ, ಆದರೆ ಹೆಚ್ಚಿದ ಜವಾಬ್ದಾರಿಗಳನ್ನು ನಿರೀಕ್ಷಿಸಿ. ಅಧಿಕಾರಿಗಳು ಪ್ರಮುಖ ಪಾತ್ರಗಳನ್ನು ವಹಿಸುತ್ತಾರೆ.",
      "ml": "ശനി നിങ്ങളുടെ കരിയർ ഭാവത്തിലൂടെ സഞ്ചരിക്കുന്നു, വെല്ലുവിളികളും അവസരങ്ങളും കൊണ്ടുവരുന്നു. കഠിനാധ്വാനം അംഗീകാരത്തിലേക്ക് നയിക്കുന്നു, എന്നാൽ വർദ്ധിച്ച ഉത്തരവാദിത്തങ്ങൾ പ്രതീക്ഷിക്കുക. അധികാര വ്യക്തികൾ പ്രധാന പങ്ക് വഹിക്കുന്നു.",
      "pa": "ਸ਼ਨੀ ਤੁਹਾਡੇ ਕਰੀਅਰ ਘਰ ਵਿੱਚ ਗੋਚਰ ਕਰ ਰਿਹਾ ਹੈ, ਚੁਣੌਤੀਆਂ ਅਤੇ ਮੌਕੇ ਦੋਵੇਂ ਲਿਆ ਰਿਹਾ ਹੈ। ਸਖ਼ਤ ਮਿਹਨਤ ਮਾਨਤਾ ਵੱਲ ਲੈ ਜਾਂਦੀ ਹੈ, ਪਰ ਵਧੀਆਂ ਜ਼ਿੰਮੇਵਾਰੀਆਂ ਦੀ ਉਮੀਦ ਕਰੋ। ਅਧਿਕਾਰੀ ਵਿਅਕਤੀ ਮਹੱਤਵਪੂਰਨ ਭੂਮਿਕਾਵਾਂ ਨਿਭਾਉਂਦੇ ਹਨ।"
    },
    "transits.saturn.signs.gemini.advice": {
      "en": "Stay dedicated to your work, maintain professional ethics, and be patient with career progress. Avoid shortcuts.",
      "hi": "अपने काम के प्रति समर्पित रहें, पेशेवर नैतिकता बनाए रखें और करियर की प्रगति के साथ धैर्य रखें। शॉर्टकट से बचें।",
      "ta": "உங்கள் வேலையில் அர்ப்பணிப்புடன் இருங்கள், தொழில்முறை நெறிமுறைகளை பராமரிக்கவும், தொழில் முன்னேற்றத்தில் பொறுமையாக இருங்கள். குறுக்கு வழிகளைத் தவிர்க்கவும்.",
      "te": "మీ పనికి అంకితభావంతో ఉండండి, వృత్తిపరమైన నీతిని కొనసాగించండి మరియు కెరీర్ పురోగతిలో సహనంగా ఉండండి. షార్ట్‌కట్‌లను నివారించండి.",
      "bn": "আপনার কাজে নিবেদিত থাকুন, পেশাদার নীতিশাস্ত্র বজায় রাখুন এবং ক্যারিয়ার অগ্রগতিতে ধৈর্য ধরুন। শর্টকাট এড়িয়ে চলুন।",
      "mr": "तुमच्या कामाशी समर्पित राहा, व्यावसायिक नैतिकता राखा आणि करिअरच्या प्रगतीबद्दल धीर धरा. शॉर्टकट टाळा.",
      "gu": "તમારા કામ પ્રત્યે સમર્પિત રહો, વ્યાવસાયિક નૈતિકતા જાળવો અને કારકિર્દીની પ્રગતિ સાથે ધીરજ રાખો. શોર્ટકટ ટાળો.",
      "kn": "ನಿಮ್ಮ ಕೆಲಸಕ್ಕೆ ಸಮರ್ಪಿತರಾಗಿರಿ, ವೃತ್ತಿಪರ ನೈತಿಕತೆಯನ್ನು ಕಾಪಾಡಿಕೊಳ್ಳಿ ಮತ್ತು ವೃತ್ತಿ ಪ್ರಗತಿಯಲ್ಲಿ ತಾಳ್ಮೆಯಿಂದಿರಿ. ಶಾರ್ಟ್‌ಕಟ್‌ಗಳನ್ನು ತಪ್ಪಿಸಿ.",
      "ml": "നിങ്ങളുടെ ജോലിയോട് സമർപ്പിതരായിരിക്കുക, പ്രൊഫഷണൽ ധാർമ്മികത നിലനിർത്തുക, കരിയർ പുരോഗതിയിൽ ക്ഷമയോടെയിരിക്കുക. കുറുക്കുവഴികൾ ഒഴിവാക്കുക.",
      "pa": "ਆਪਣੇ ਕੰਮ ਪ੍ਰਤੀ ਸਮਰਪਿਤ ਰਹੋ, ਪੇਸ਼ੇਵਰ ਨੈਤਿਕਤਾ ਬਣਾਈ ਰੱਖੋ ਅਤੇ ਕਰੀਅਰ ਦੀ ਤਰੱਕੀ ਨਾਲ ਧੀਰਜ ਰੱਖੋ। ਸ਼ਾਰਟਕੱਟ ਤੋਂ ਬਚੋ।"
    },
    "transits.saturn.signs.cancer.name": {
      "en": "Cancer",
      "hi": "कर्क",
      "ta": "கடகம்",
      "te": "కర్కాటకం",
      "bn": "কর্কট",
      "mr": "कर्क",
      "gu": "કર્ક",
      "kn": "ಕರ್ಕಾಟಕ",
      "ml": "കർക്കടകം",
      "pa": "ਕਰਕ"
    },
    "transits.saturn.signs.cancer.house": {
      "en": "9th House",
      "hi": "9वां भाव",
      "ta": "9வது வீடு",
      "te": "9వ భావం",
      "bn": "9তম ভাব",
      "mr": "9वे स्थान",
      "gu": "9મું ઘર",
      "kn": "9ನೇ ಮನೆ",
      "ml": "9-ാം ഭാവം",
      "pa": "9ਵਾਂ ਘਰ"
    },
    "transits.saturn.signs.cancer.effect": {
      "en": "Favorable",
      "hi": "अनुकूल",
      "ta": "சாதகமான",
      "te": "అనుకూలం",
      "bn": "অনুকূল",
      "mr": "अनुकूल",
      "gu": "અનુકૂળ",
      "kn": "ಅನುಕೂಲ",
      "ml": "അനുകൂലം",
      "pa": "ਅਨੁਕੂਲ"
    },
    "transits.saturn.signs.cancer.description": {
      "en": "Saturn in your 9th house supports higher learning, long-distance travel, and spiritual growth. Father figures and teachers play important roles. Legal matters are favored.",
      "hi": "आपके 9वें भाव में शनि उच्च शिक्षा, लंबी दूरी की यात्रा और आध्यात्मिक विकास का समर्थन करता है। पिता तुल्य व्यक्ति और शिक्षक महत्वपूर्ण भूमिका निभाते हैं। कानूनी मामले अनुकूल हैं।",
      "ta": "உங்கள் 9வது வீட்டில் சனி உயர் கல்வி, நீண்ட தூர பயணம் மற்றும் ஆன்மீக வளர்ச்சியை ஆதரிக்கிறது. தந்தை நபர்களும் ஆசிரியர்களும் முக்கிய பங்கு வகிக்கின்றனர். சட்ட விவகாரங்கள் சாதகமானவை.",
      "te": "మీ 9వ భావంలో శని ఉన్నత విద్య, దూర ప్రయాణం మరియు ఆధ్యాత్మిక వృద్ధికి మద్దతు ఇస్తుంది. తండ్రి వ్యక్తులు మరియు ఉపాధ్యాయులు ముఖ్యమైన పాత్రలు పోషిస్తారు. న్యాయ విషయాలు అనుకూలంగా ఉంటాయి.",
      "bn": "আপনার 9তম ভাবে শনি উচ্চ শিক্ষা, দূর ভ্রমণ এবং আধ্যাত্মিক বৃদ্ধিকে সমর্থন করে। পিতৃ ব্যক্তি এবং শিক্ষকরা গুরুত্বপূর্ণ ভূমিকা পালন করে। আইনি বিষয়গুলি অনুকূল।",
      "mr": "तुमच्या 9व्या स्थानात शनि उच्च शिक्षण, लांब पल्ल्याचा प्रवास आणि आध्यात्मिक वाढीस समर्थन देतो. पितृ व्यक्ती आणि शिक्षक महत्त्वाची भूमिका बजावतात. कायदेशीर बाबी अनुकूल आहेत.",
      "gu": "તમારા 9મા ઘરમાં શનિ ઉચ્ચ શિક્ષણ, લાંબા અંતરની મુસાફરી અને આધ્યાત્મિક વિકાસને સમર્થન આપે છે. પિતૃ વ્યક્તિઓ અને શિક્ષકો મહત્વપૂર્ણ ભૂમિકા ભજવે છે. કાનૂની બાબતો અનુકૂળ છે.",
      "kn": "ನಿಮ್ಮ 9ನೇ ಮನೆಯಲ್ಲಿ ಶನಿ ಉನ್ನತ ಶಿಕ್ಷಣ, ದೂರ ಪ್ರಯಾಣ ಮತ್ತು ಆಧ್ಯಾತ್ಮಿಕ ಬೆಳವಣಿಗೆಯನ್ನು ಬೆಂಬಲಿಸುತ್ತದೆ. ತಂದೆಯ ವ್ಯಕ್ತಿಗಳು ಮತ್ತು ಶಿಕ್ಷಕರು ಪ್ರಮುಖ ಪಾತ್ರಗಳನ್ನು ವಹಿಸುತ್ತಾರೆ. ಕಾನೂನು ವಿಷಯಗಳು ಅನುಕೂಲಕರ.",
      "ml": "നിങ്ങളുടെ 9-ാം ഭാവത്തിൽ ശനി ഉന്നത വിദ്യാഭ്യാസം, ദൂര യാത്ര, ആത്മീയ വളർച്ച എന്നിവയെ പിന്തുണയ്ക്കുന്നു. പിതൃ വ്യക്തികളും അധ്യാപകരും പ്രധാന പങ്ക് വഹിക്കുന്നു. നിയമ കാര്യങ്ങൾ അനുകൂലമാണ്.",
      "pa": "ਤੁਹਾਡੇ 9ਵੇਂ ਘਰ ਵਿੱਚ ਸ਼ਨੀ ਉੱਚ ਸਿੱਖਿਆ, ਲੰਬੀ ਦੂਰੀ ਦੀ ਯਾਤਰਾ ਅਤੇ ਅਧਿਆਤਮਿਕ ਵਿਕਾਸ ਦਾ ਸਮਰਥਨ ਕਰਦਾ ਹੈ। ਪਿਤਾ ਵਰਗੇ ਵਿਅਕਤੀ ਅਤੇ ਅਧਿਆਪਕ ਮਹੱਤਵਪੂਰਨ ਭੂਮਿਕਾਵਾਂ ਨਿਭਾਉਂਦੇ ਹਨ। ਕਾਨੂੰਨੀ ਮਾਮਲੇ ਅਨੁਕੂਲ ਹਨ।"
    },
    "transits.saturn.signs.cancer.advice": {
      "en": "Pursue higher education, plan meaningful travels, and strengthen your spiritual foundation. Respect elders and teachers.",
      "hi": "उच्च शिक्षा प्राप्त करें, सार्थक यात्राओं की योजना बनाएं और अपनी आध्यात्मिक नींव को मजबूत करें। बड़ों और शिक्षकों का सम्मान करें।",
      "ta": "உயர் கல்வியைத் தொடருங்கள், அர்த்தமுள்ள பயணங்களைத் திட்டமிடுங்கள், உங்கள் ஆன்மீக அடித்தளத்தை வலுப்படுத்துங்கள். பெரியவர்களையும் ஆசிரியர்களையும் மதிக்கவும்.",
      "te": "ఉన్నత విద్యను అనుసరించండి, అర్థవంతమైన ప్రయాణాలను ప్లాన్ చేయండి మరియు మీ ఆధ్యాత్మిక పునాదిని బలపరచండి. పెద్దలను మరియు ఉపాధ్యాయులను గౌరవించండి.",
      "bn": "উচ্চ শিক্ষা অনুসরণ করুন, অর্থবহ ভ্রমণের পরিকল্পনা করুন এবং আপনার আধ্যাত্মিক ভিত্তি শক্তিশালী করুন। বড়দের এবং শিক্ষকদের সম্মান করুন।",
      "mr": "उच्च शिक्षण घ्या, अर्थपूर्ण प्रवासांचे नियोजन करा आणि तुमचा आध्यात्मिक पाया मजबूत करा. वडीलधाऱ्यांचा आणि शिक्षकांचा आदर करा.",
      "gu": "ઉચ્ચ શિક્ષણ મેળવો, અર્થપૂર્ણ મુસાફરીનું આયોજન કરો અને તમારા આધ્યાત્મિક પાયાને મજબૂત કરો. વડીલો અને શિક્ષકોનો આદર કરો.",
      "kn": "ಉನ್ನತ ಶಿಕ್ಷಣವನ್ನು ಅನುಸರಿಸಿ, ಅರ್ಥಪೂರ್ಣ ಪ್ರಯಾಣಗಳನ್ನು ಯೋಜಿಸಿ ಮತ್ತು ನಿಮ್ಮ ಆಧ್ಯಾತ್ಮಿಕ ಅಡಿಪಾಯವನ್ನು ಬಲಪಡಿಸಿ. ಹಿರಿಯರು ಮತ್ತು ಶಿಕ್ಷಕರನ್ನು ಗೌರವಿಸಿ.",
      "ml": "ഉന്നത വിദ്യാഭ്യാസം പിന്തുടരുക, അർത്ഥവത്തായ യാത്രകൾ ആസൂത്രണം ചെയ്യുക, നിങ്ങളുടെ ആത്മീയ അടിത്തറ ശക്തിപ്പെടുത്തുക. മുതിർന്നവരെയും അധ്യാപകരെയും ബഹുമാനിക്കുക.",
      "pa": "ਉੱਚ ਸਿੱਖਿਆ ਪ੍ਰਾਪਤ ਕਰੋ, ਅਰਥਪੂਰਨ ਯਾਤਰਾਵਾਂ ਦੀ ਯੋਜਨਾ ਬਣਾਓ ਅਤੇ ਆਪਣੀ ਅਧਿਆਤਮਿਕ ਨੀਂਹ ਨੂੰ ਮਜ਼ਬੂਤ ਕਰੋ। ਬਜ਼ੁਰਗਾਂ ਅਤੇ ਅਧਿਆਪਕਾਂ ਦਾ ਸਤਿਕਾਰ ਕਰੋ।"
    }
  }
}
